Workbook

Sheet Top Sheet
A1: TALHA GROUP
A2: Corporate Headquarter: Anabil Tower (12th & 13th Floor), Plot # 3, Block NW(J), Kamal Ataturk Avenue, Gulshan-2, Dhaka-1212. Corporate Head Office: Grand Delvistaa, Level-7, House - CES(A) 1/A, Road-113, Gulshan Avenue, Gulshan-2, Dhaka-1212.
A5: Employee Appraisal Summary
A6: Overall Structure: HOD 50% + HR 30% + Internal Audit 20%
H7: Department Name | J7: Grade / Band:
A8: Department Name: | B8: ICT (Local Software) | D8: Employee Position: | E8: Senior and Entry
A9: Appraisal Type: | B9: Yearly | D9: Assessment Period: | E9: 2025-2026 | H9: Corporate Accounts | J9: Band 1
H10: Factory Accounts | J10: Band 2
A11: Employee Name: | B11: Navid Anjum Shuvro | C11: Designation: | D11: SOFTWARE DEVELOPMENT SPECIALIST | H11: Corporate Accounts (Vat and Tax) | J11: Band 3
A12: Employee ID: | B12: 8365 | C12: Grade / Band: | D12: Band 11 | H12: Corporate Finance | J12: Band 4
A13: Current Gross Salary: | B13: 72000 | C13: Date of Joining: | D13: 45292 | H13: Cash and Treasury | J13: Band 5
A14: Cut-off Date: | B14: 46195 | C14: Service Length: | D14: =IF(OR(D13="",B14=""),"",(YEAR(B14)-YEAR(D13)-IF(DATE(YEAR(B14),MONTH(D13),DAY(D13))>B14,1,0))&" Y "&(MONTH(B14)-MONTH(D13)+IF(DAY(B14)<DAY(D13),-1,0)+IF(MONTH(B14)-MONTH(D13)+IF(DAY(B14)<DAY(D13),-1,0)<0,12,0))&" M "&(B14-DATE(YEAR(B14),MONTH(B14)-IF(DAY(B14)<DAY(D13),1,0),DAY(D13)))&" D") -> 2 Y 5 M 21 D | H14: Export Commercial (Bond and Customs) | J14: Band 6
H15: Export Commercial | J15: Band 7
H16: Import Commercial (LC Operations and Settlements) | J16: Band 8
A17: Evaluator | B17: Weight | C17: Score (Out of 100) | D17: Weighted Score | E17: Remarks | H17: Import Commercial (C&F and Logistic Communication) | J17: Band 9
A18: HOD | B18: 50 | C18: =IFERROR('Part A - HOD (50%)'!$G$25,"") -> 100 | D18: =IF(C18="","",C18*B18/100) -> 50 | H18: Regulatory Affairs and Compliance | J18: Band 10
A19: HR | B19: 30 | C19: =IFERROR('Part B - HR (30%)'!$G$18,"") -> 100 | D19: =IF(C19="","",C19*B19/100) -> 30 | H19: Local Sourcing and Procurement | J19: Band 11
A20: Internal Audit | B20: 20 | C20: =IFERROR('Part C - Audit (20%)'!$G$18,"") -> 100 | D20: =IF(C20="","",C20*B20/100) -> 20 | H20: Global Sourcing and Procurement | J20: Band 12
A21: Total | B21: 100 | C21: =IF(D21="","",D21) -> 100 | D21: =IF(SUM(D18:D20)=0,"",SUM(D18:D20)) -> 100 | H21: Textile Marketing & Development | J21: Band 13
H22: Corporate HR and Admin | J22: Band 14
A23: Overall Rating based on Weighted Score | H23: ICT (Operation) | J23: Band 15
A24: Rating | B24: =IF(D21="","",IF(D21>=90,"Excellent",IF(D21>=80,"Very Good",IF(D21>=70,"Good",IF(D21>=60,"Needs Improvement","Unsatisfactory"))))) -> Excellent | H24: ICT (Local Software) | J24: Band 16
H25: ICT (ERP) | J25: Band 17
A26: Recommended Management Actions | H26: Warp Knit Marketing | J26: Band 18
B27: Promotion to | D27: Grade/Band: | H27: Costing and Pricing | J27: Band 19
B28: Increment of BDT | D28: Gross after Inc. | E28: =C28+B13 -> 72000 | H28: Local Sales (wastage, Leftover and Others) | J28: Band 20
B29: Training and development plan | H29: Accessories Marketing | J29: Band 21
B30: No increment + PIP | H30: Internal Audit
B31: Role review / disciplinary action
A34: Authorized Signatures (HR and Final Approval Authority)

Sheet Part A - HOD (50%)
A1: PART A — PERFORMANCE ASSESSMENT BY HOD | Functional & Leadership Evaluation – 50% | Position – Below Lead
A2: Employee: | B2: ='Top Sheet'!B11 -> Navid Anjum Shuvro | D2: Employee ID: | F2: ='Top Sheet'!B12 -> 8365 | G2: Grade: | H2: ='Top Sheet'!D12 -> Band 11
A3: Designation: | B3: ='Top Sheet'!D11 -> SOFTWARE DEVELOPMENT SPECIALIST | D3: Appraisal Period: | F3: ='Top Sheet'!E9 -> 2025-2026 | G3: Current Gross Salary: | H3: ='Top Sheet'!B13 -> 72000
A4: Date of Joining: | B4: ='Top Sheet'!D13 -> 45292 | D4: Service Length: | F4: ='Top Sheet'!D14 -> 2 Y 5 M 21 D | G4: Gross after P. Incr.: | H4: =IF(C29="","",H3+C29)
A5: Rating Scale: 5 = Excellent | 4 = Very Good | 3 = Good | 2 = Needs Improvement | 1 = Poor | Max Score = 5
A6: Sl. | B6: Key Performance Area / Competency Area | D6: Weight | E6: Assessment Focus | F6: Score (1–5) | G6: Weighted Score | H6: Remarks
A7: 1 | B7: Assigned Software Task Execution | D7: 0.04 | E7: Completes assigned software support, development, configuration, or data-related tasks accurately and within required timeline. | F7: 5 | G7: =IF(F7="","",(F7/5)*D7) -> 0.04 | H7: =IF(F7="","—",IF(F7=5,"Excellent",IF(F7=4,"Very Good",IF(F7=3,"Good",IF(F7=2,"Needs Improvement","Poor"))))) -> Excellent
A8: 2 | B8: User Support, Troubleshooting & Issue Resolution | D8: 0.05 | E8: Provides timely support for user problems, software errors, login issues, report issues, and basic troubleshooting. | F8: 5 | G8: =IF(F8="","",(F8/5)*D8) -> 0.05 | H8: =IF(F8="","—",IF(F8=5,"Excellent",IF(F8=4,"Very Good",IF(F8=3,"Good",IF(F8=2,"Needs Improvement","Poor"))))) -> Excellent
A9: 3 | B9: Requirement Collection & Clarification Support | D9: 0.03 | E9: Collects user requirements, clarifies business needs, documents required changes, and informs supervisor properly. | F9: 5 | G9: =IF(F9="","",(F9/5)*D9) -> 0.03 | H9: =IF(F9="","—",IF(F9=5,"Excellent",IF(F9=4,"Very Good",IF(F9=3,"Good",IF(F9=2,"Needs Improvement","Poor"))))) -> Excellent
A10: 4 | B10: Software Development, Customization & Configuration Support | D10: 0.05 | E10: Supports coding, customization, configuration, form/report development, and approved software changes as assigned. | F10: 5 | G10: =IF(F10="","",(F10/5)*D10) -> 0.05 | H10: =IF(F10="","—",IF(F10=5,"Excellent",IF(F10=4,"Very Good",IF(F10=3,"Good",IF(F10=2,"Needs Improvement","Poor"))))) -> Excellent
A11: 5 | B11: Bug Fixing, Testing & UAT Support | D11: 0.04 | E11: Supports bug fixing, testing, UAT, user feedback collection, and correction before final deployment. | F11: 5 | G11: =IF(F11="","",(F11/5)*D11) -> 0.04 | H11: =IF(F11="","—",IF(F11=5,"Excellent",IF(F11=4,"Very Good",IF(F11=3,"Good",IF(F11=2,"Needs Improvement","Poor"))))) -> Excellent
A12: 6 | B12: Report, Query, Dashboard & MIS Support | D12: 0.03 | E12: Supports preparation of reports, queries, dashboards, data extracts, and MIS as per user or management requirement. | F12: 5 | G12: =IF(F12="","",(F12/5)*D12) -> 0.03 | H12: =IF(F12="","—",IF(F12=5,"Excellent",IF(F12=4,"Very Good",IF(F12=3,"Good",IF(F12=2,"Needs Improvement","Poor"))))) -> Excellent
A13: 7 | B13: Database, Data Checking & Data Accuracy Support | D13: 0.03 | E13: Supports database checking, data validation, correction support, duplicate checking, and data accuracy review. | F13: 5 | G13: =IF(F13="","",(F13/5)*D13) -> 0.03 | H13: =IF(F13="","—",IF(F13=5,"Excellent",IF(F13=4,"Very Good",IF(F13=3,"Good",IF(F13=2,"Needs Improvement","Poor"))))) -> Excellent
A14: 8 | B14: Deployment, Update & Version Support | D14: 0.03 | E14: Supports software deployment, patch update, version update, release note, and post-deployment checking. | F14: 5 | G14: =IF(F14="","",(F14/5)*D14) -> 0.03 | H14: =IF(F14="","—",IF(F14=5,"Excellent",IF(F14=4,"Very Good",IF(F14=3,"Good",IF(F14=2,"Needs Improvement","Poor"))))) -> Excellent
A15: 9 | B15: Documentation, User Manual & SOP Support | D15: 0.03 | E15: Maintains user manuals, process notes, change records, troubleshooting notes, and software-related documentation. | F15: 5 | G15: =IF(F15="","",(F15/5)*D15) -> 0.03 | H15: =IF(F15="","—",IF(F15=5,"Excellent",IF(F15=4,"Very Good",IF(F15=3,"Good",IF(F15=2,"Needs Improvement","Poor"))))) -> Excellent
A16: 10 | B16: User Training & Communication Support | D16: 0.03 | E16: Supports user training, system guidance, issue explanation, and communication with departments in a professional manner. | F16: 5 | G16: =IF(F16="","",(F16/5)*D16) -> 0.03 | H16: =IF(F16="","—",IF(F16=5,"Excellent",IF(F16=4,"Very Good",IF(F16=3,"Good",IF(F16=2,"Needs Improvement","Poor"))))) -> Excellent
A17: 11 | B17: Access Request, Permission & Setup Support | D17: 0.02 | E17: Supports user access setup, permission change, password reset, account creation, and approved access-related activities. | F17: 5 | G17: =IF(F17="","",(F17/5)*D17) -> 0.02 | H17: =IF(F17="","—",IF(F17=5,"Excellent",IF(F17=4,"Very Good",IF(F17=3,"Good",IF(F17=2,"Needs Improvement","Poor"))))) -> Excellent
A18: 12 | B18: Backup, Security & Compliance Support | D18: 0.03 | E18: Supports backup checking, basic software security, access discipline, and reports security or compliance concerns. | F18: 5 | G18: =IF(F18="","",(F18/5)*D18) -> 0.03 | H18: =IF(F18="","—",IF(F18=5,"Excellent",IF(F18=4,"Very Good",IF(F18=3,"Good",IF(F18=2,"Needs Improvement","Poor"))))) -> Excellent
... A23: 17 | B23: Accountability, Decision Making & Pressure Handling | D23: 0.01 | E23: Shows ownership, sound judgment and professional decision-making while handling urgent regulatory, audit and operational pressure. | F23: 5 | G23: =IF(F23="","",(F23/5)*D23) -> 0.01 | H23: =IF(F23="","—",IF(F23=5,"Excellent",IF(F23=4,"Very Good",IF(F23=3,"Good",IF(F23=2,"Needs Improvement","Poor"))))) -> Excellent
A24: TOTAL | D24: =SUM(D7:D23) -> 0.5 | F24: =SUM(F7:F23) -> 85 | G24: =IFERROR(SUM(G7:G23),"") -> 0.5
A25: HOD Block Score (out of 100): | G25: =IFERROR(G24/0.5*100,"") -> 100 | H25: =IFERROR(IF(G25>=90,"Excellent",IF(G25>=80,"Very Good",IF(G25>=70,"Good",IF(G25>=60,"Needs Improvement","Unsatisfactory")))),"—") -> Excellent
A27: Recommended Actions:
B28: Promotion to
B29: Increment of BDT
B30: No Increment + PIP
B31: PIP / Role Review / Disciplinary Action
A33: HOD Comments (if any) and Signature with Seal and Date:

Sheet Part B - HR (30%)
A1: PART B — PERFORMANCE ASSESSMENT BY HR | Behavioral, Leadership & Policy Evaluation – 30% | Position – Below Lead
A2: Employee: | B2: ='Top Sheet'!B11 -> Navid Anjum Shuvro | D2: Employee ID: | F2: ='Top Sheet'!B12 -> 8365 | G2: Grade: | H2: ='Top Sheet'!D12 -> Band 11
A3: Designation: | B3: ='Top Sheet'!D11 -> SOFTWARE DEVELOPMENT SPECIALIST | D3: Appraisal Period: | F3: ='Top Sheet'!E9 -> 2025-2026 | G3: Current Gross Salary: | H3: ='Top Sheet'!B13 -> 72000
A4: Date of Joining: | B4: ='Top Sheet'!D13 -> 45292 | D4: Service Length: | F4: ='Top Sheet'!D14 -> 2 Y 5 M 21 D | G4: Gross after P. Incr.: | H4: =IF(C22="","",H3+C22)
A5: Rating Scale: 5 = Excellent | 4 = Very Good | 3 = Good | 2 = Needs Improvement | 1 = Poor | Max Score = 5
A6: Sl. | B6: Key Performance Area / Competency Area | D6: Weight | E6: Assessment Focus | F6: Score (1–5) | G6: Weighted Score | H6: Remarks
A7: 1 | B7: Attendance, Punctuality, Leave Discipline & Office Discipline | D7: 0.05 | E7: Maintains regular attendance, punctuality, leave discipline, reporting discipline and sets a positive example for team members. | F7: 5 | G7: =IF(F7="","",(F7/5)*D7) -> 0.05 | H7: =IF(F7="","—",IF(F7=5,"Excellent",IF(F7=4,"Very Good",IF(F7=3,"Good",IF(F7=2,"Needs Improvement","Poor"))))) -> Excellent
A8: 2 | B8: Adherence to HR Policies, Code of Conduct & Company Rules | D8: 0.04 | E8: Follows HR policies, company rules, code of conduct, employment terms and workplace standards consistently. | F8: 5 | G8: =IF(F8="","",(F8/5)*D8) -> 0.04 | H8: =IF(F8="","—",IF(F8=5,"Excellent",IF(F8=4,"Very Good",IF(F8=3,"Good",IF(F8=2,"Needs Improvement","Poor"))))) -> Excellent
A9: 3 | B9: Professional Behavior & Positive Attitude | D9: 0.04 | E9: Demonstrates maturity, respect, responsibility, cooperation, and positive workplace behavior. | F9: 5 | G9: =IF(F9="","",(F9/5)*D9) -> 0.04 | H9: =IF(F9="","—",IF(F9=5,"Excellent",IF(F9=4,"Very Good",IF(F9=3,"Good",IF(F9=2,"Needs Improvement","Poor"))))) -> Excellent
A10: 4 | B10: Teamwork & Cooperation | D10: 0.03 | E10: Works cooperatively with team members and other departments and supports departmental goals. | F10: 5 | G10: =IF(F10="","",(F10/5)*D10) -> 0.03 | H10: =IF(F10="","—",IF(F10=5,"Excellent",IF(F10=4,"Very Good",IF(F10=3,"Good",IF(F10=2,"Needs Improvement","Poor"))))) -> Excellent
A11: 5 | B11: Communication & Professional Etiquette | D11: 0.02 | E11: Communicates clearly, politely, and professionally with supervisors, colleagues, HR, and other departments. | F11: 5 | G11: =IF(F11="","",(F11/5)*D11) -> 0.02 | H11: =IF(F11="","—",IF(F11=5,"Excellent",IF(F11=4,"Very Good",IF(F11=3,"Good",IF(F11=2,"Needs Improvement","Poor"))))) -> Excellent
A12: 6 | B12: Honesty, Integrity & Ethical Conduct | D12: 0.03 | E12: Maintains honesty, transparency, ethical behavior, and avoids conflict of interest or misuse of company resources. | F12: 5 | G12: =IF(F12="","",(F12/5)*D12) -> 0.03 | H12: =IF(F12="","—",IF(F12=5,"Excellent",IF(F12=4,"Very Good",IF(F12=3,"Good",IF(F12=2,"Needs Improvement","Poor"))))) -> Excellent
A13: 7 | B13: Confidentiality of Company Information | D13: 0.02 | E13: Protects confidential company, regulatory, legal, employee, financial, supplier, customer, and management information. | F13: 5 | G13: =IF(F13="","",(F13/5)*D13) -> 0.02 | H13: =IF(F13="","—",IF(F13=5,"Excellent",IF(F13=4,"Very Good",IF(F13=3,"Good",IF(F13=2,"Needs Improvement","Poor"))))) -> Excellent
A14: 8 | B14: Compliance with HR Processes & Documentation | D14: 0.03 | E14: Completes HR-related processes properly, including attendance correction, leave application, appraisal information, and required documents. | F14: 5 | G14: =IF(F14="","",(F14/5)*D14) -> 0.03 | H14: =IF(F14="","—",IF(F14=5,"Excellent",IF(F14=4,"Very Good",IF(F14=3,"Good",IF(F14=2,"Needs Improvement","Poor"))))) -> Excellent
A15: 9 | B15: Learning Attitude, Adaptability & Improvement Mindset | D15: 0.02 | E15: Shows willingness to learn, accepts feedback, adapts to new systems/processes, and improves performance. | F15: 5 | G15: =IF(F15="","",(F15/5)*D15) -> 0.02 | H15: =IF(F15="","—",IF(F15=5,"Excellent",IF(F15=4,"Very Good",IF(F15=3,"Good",IF(F15=2,"Needs Improvement","Poor"))))) -> Excellent
A16: 10 | B16: Company Asset Care, Safety & Workplace Cleanliness | D16: 0.02 | E16: Uses company assets responsibly and supports workplace safety, security, and cleanliness. | F16: 5 | G16: =IF(F16="","",(F16/5)*D16) -> 0.02 | H16: =IF(F16="","—",IF(F16=5,"Excellent",IF(F16=4,"Very Good",IF(F16=3,"Good",IF(F16=2,"Needs Improvement","Poor"))))) -> Excellent
A17: TOTAL | D17: =SUM(D7:D16) -> 0.3 | F17: =SUM(F7:F16) -> 50 | G17: =IFERROR(SUM(G7:G16),"") -> 0.3
A18: HR Block Score (out of 100): | G18: =IFERROR(G17/0.3*100,"") -> 100 | H18: =IFERROR(IF(G18>=90,"Excellent",IF(G18>=80,"Very Good",IF(G18>=70,"Good",IF(G18>=60,"Needs Improvement","Unsatisfactory")))),"—") -> Excellent
A20: Recommended Actions:
B21: Promotion to | F21: No of Software Develop and Follow-up: | H21: 16
B22: Increment of BDT
B23: No Increment + PIP
B24: PIP / Role Review / Disciplinary Action
A26: HR Comments (if any) and Signature with Seal and Date:

Sheet Part C - Audit (20%)
A1: PART C — PERFORMANCE ASSESSMENT BY AUDIT | Bond Control & Compliance – 20% | Position – Below Lead
A2: Employee: | B2: ='Top Sheet'!B11 -> Navid Anjum Shuvro | D2: Employee ID: | F2: ='Top Sheet'!B12 -> 8365 | G2: Grade: | H2: ='Top Sheet'!D12 -> Band 11
A3: Designation: | B3: ='Top Sheet'!D11 -> SOFTWARE DEVELOPMENT SPECIALIST | D3: Appraisal Period: | F3: ='Top Sheet'!E9 -> 2025-2026 | G3: Current Gross Salary: | H3: ='Top Sheet'!B13 -> 72000
A4: Date of Joining: | B4: ='Top Sheet'!D13 -> 45292 | D4: Service Length: | F4: ='Top Sheet'!D14 -> 2 Y 5 M 21 D | G4: Gross after P. Incr.: | H4: =IF(C22="","",H3+C22)
A5: Rating Scale: 5 = Excellent | 4 = Very Good | 3 = Good | 2 = Needs Improvement | 1 = Poor | Max Score = 5
A6: Sl. | B6: Key Performance Area / Competency Area | D6: Weight | E6: Assessment Focus | F6: Score (1–5) | G6: Weighted Score | H6: Remarks
A7: 1 | B7: Compliance with Software SOP, ICT Policy & Approval Process | D7: 0.03 | E7: Follows software SOP, ICT policy, access policy, change approval process, and company control requirements. | F7: 5 | G7: =IF(F7="","",(F7/5)*D7) -> 0.03 | H7: =IF(F7="","—",IF(F7=5,"Excellent",IF(F7=4,"Very Good",IF(F7=3,"Good",IF(F7=2,"Needs Improvement","Poor"))))) -> Excellent
A8: 2 | B8: Access Request, Approval & Permission Evidence Support | D8: 0.03 | E8: Maintains evidence for access request, permission change, password reset, user account creation, and access removal. | F8: 5 | G8: =IF(F8="","",(F8/5)*D8) -> 0.03 | H8: =IF(F8="","—",IF(F8=5,"Excellent",IF(F8=4,"Very Good",IF(F8=3,"Good",IF(F8=2,"Needs Improvement","Poor"))))) -> Excellent
A9: 3 | B9: Change, Testing & Deployment Documentation Support | D9: 0.03 | E9: Maintains support documents for software change request, testing, UAT, deployment, version update, and release records. | F9: 5 | G9: =IF(F9="","",(F9/5)*D9) -> 0.03 | H9: =IF(F9="","—",IF(F9=5,"Excellent",IF(F9=4,"Very Good",IF(F9=3,"Good",IF(F9=2,"Needs Improvement","Poor"))))) -> Excellent
A10: 4 | B10: Data Backup, Security & Control Evidence Support | D10: 0.02 | E10: Supports backup evidence, data protection, security checking, and control-related documentation. | F10: 5 | G10: =IF(F10="","",(F10/5)*D10) -> 0.02 | H10: =IF(F10="","—",IF(F10=5,"Excellent",IF(F10=4,"Very Good",IF(F10=3,"Good",IF(F10=2,"Needs Improvement","Poor"))))) -> Excellent
A11: 5 | B11: Bug, Ticket, Service Log & Incident Documentation | D11: 0.03 | E11: Maintains complete bug reports, support tickets, service logs, incident notes, and resolution evidence. | F11: 5 | G11: =IF(F11="","",(F11/5)*D11) -> 0.03 | H11: =IF(F11="","—",IF(F11=5,"Excellent",IF(F11=4,"Very Good",IF(F11=3,"Good",IF(F11=2,"Needs Improvement","Poor"))))) -> Excellent
A12: 6 | B12: Audit Observation Correction Support | D12: 0.02 | E12: Supports correction of audit observations, provides documents, and helps prevent repeat mistakes in assigned work. | F12: 5 | G12: =IF(F12="","",(F12/5)*D12) -> 0.02 | H12: =IF(F12="","—",IF(F12=5,"Excellent",IF(F12=4,"Very Good",IF(F12=3,"Good",IF(F12=2,"Needs Improvement","Poor"))))) -> Excellent
A13: 7 | B13: System, Data & Report Reliability | D13: 0.01 | E13: Ensures software data, reports, queries, tracking files, and MIS outputs are accurate and reliable. | F13: 5 | G13: =IF(F13="","",(F13/5)*D13) -> 0.01 | H13: =IF(F13="","—",IF(F13=5,"Excellent",IF(F13=4,"Very Good",IF(F13=3,"Good",IF(F13=2,"Needs Improvement","Poor"))))) -> Excellent
A14: 8 | B14: Timely Response to Audit Queries & Cooperation | D14: 0.01 | E14: Provides documents, clarification, and cooperation to Internal Audit within required timeline. | F14: 5 | G14: =IF(F14="","",(F14/5)*D14) -> 0.01 | H14: =IF(F14="","—",IF(F14=5,"Excellent",IF(F14=4,"Very Good",IF(F14=3,"Good",IF(F14=2,"Needs Improvement","Poor"))))) -> Excellent
A15: 9 | B15: Unauthorized Access, Data Leakage & Software Misuse Awareness | D15: 0.01 | E15: Remains alert to unauthorized access, data leakage, password sharing, system misuse, or ICT policy violation. | F15: 5 | G15: =IF(F15="","",(F15/5)*D15) -> 0.01 | H15: =IF(F15="","—",IF(F15=5,"Excellent",IF(F15=4,"Very Good",IF(F15=3,"Good",IF(F15=2,"Needs Improvement","Poor"))))) -> Excellent
A16: 10 | B16: Integrity, Transparency & Compliance Mindset | D16: 0.01 | E16: Demonstrates honesty, transparency, ethical conduct, and compliance mindset in local software activities. | F16: 5 | G16: =IF(F16="","",(F16/5)*D16) -> 0.01 | H16: =IF(F16="","—",IF(F16=5,"Excellent",IF(F16=4,"Very Good",IF(F16=3,"Good",IF(F16=2,"Needs Improvement","Poor"))))) -> Excellent
A17: TOTAL | D17: =SUM(D7:D16) -> 0.2 | F17: =SUM(F7:F16) -> 50 | G17: =IFERROR(SUM(G7:G16),"") -> 0.2
A18: Audit Block Score (out of 100): | G18: =IFERROR(G17/0.2*100,"") -> 100 | H18: =IFERROR(IF(G18>=90,"Excellent",IF(G18>=80,"Very Good",IF(G18>=70,"Good",IF(G18>=60,"Needs Improvement","Unsatisfactory")))),"—") -> Excellent
A20: Recommended Actions:
B21: Promotion to
B22: Increment of BDT
B23: No Increment + PIP
B24: PIP / Role Review / Disciplinary Action
A26: Audit Comments (if any) and Signature with Seal and Date:

Sheet Part A - HOD (50%) (2)
A1: PART A — PERFORMANCE ASSESSMENT BY HOD | Functional & Leadership Evaluation – 50% | Position – Lead & Above
A2: Employee: | B2: ='Top Sheet'!B11 -> Navid Anjum Shuvro | D2: Employee ID: | F2: ='Top Sheet'!B12 -> 8365 | G2: Grade: | H2: ='Top Sheet'!D12 -> Band 11
A3: Designation: | B3: ='Top Sheet'!D11 -> SOFTWARE DEVELOPMENT SPECIALIST | D3: Appraisal Period: | F3: ='Top Sheet'!E9 -> 2025-2026 | G3: Current Gross Salary: | H3: ='Top Sheet'!B13 -> 72000
A4: Date of Joining: | B4: ='Top Sheet'!D13 -> 45292 | D4: Service Length: | F4: ='Top Sheet'!D14 -> 2 Y 5 M 21 D | G4: Gross after P. Incr.: | H4: =IF(C27="","",H3+C27)
A5: Rating Scale: 5 = Excellent | 4 = Very Good | 3 = Good | 2 = Needs Improvement | 1 = Poor | Max Score = 5
A6: Sl. | B6: Key Performance Area / Competency Area | D6: Weight | E6: Assessment Focus | F6: Score (1–5) | G6: Weighted Score | H6: Remarks
A7: 1 | B7: Export Operation Supervision & Departmental Execution | D7: 0.05 | E7: Supervises export commercial activities regularly and efficiently from shipment/export operation up to document submission, ETA/destination follow-up and final payment coordination. | G7: =IF(F7="","",(F7/5)*D7) | H7: =IF(F7="","—",IF(F7=5,"Excellent",IF(F7=4,"Very Good",IF(F7=3,"Good",IF(F7=2,"Needs Improvement","Poor"))))) -> —
A8: 2 | B8: Team Leadership, Work Distribution and Supervision | D8: 0.04 | E8: Leads/supervises team members, monitors delegated work, guides problem-solving and ensures timely completion of export commercial responsibilities. | G8: =IF(F8="","",(F8/5)*D8) | H8: =IF(F8="","—",IF(F8=5,"Excellent",IF(F8=4,"Very Good",IF(F8=3,"Good",IF(F8=2,"Needs Improvement","Poor"))))) -> —
A9: 3 | B9: Problem Solving, Decision Making and Emergency Support | D9: 0.03 | E9: Handles document issues, vessel/cargo release matters, overdue/duplication problems and urgent official requirements with ownership and maturity. | G9: =IF(F9="","",(F9/5)*D9) | H9: =IF(F9="","—",IF(F9=5,"Excellent",IF(F9=4,"Very Good",IF(F9=3,"Good",IF(F9=2,"Needs Improvement","Poor"))))) -> —
A10: 4 | B10: Final Bank Document Submission as per L/C | D10: 0.04 | E10: Ensures timely and accurate final export/bank document submission according to L/C, buyer and bank requirements; monitors pending submissions and discrepancy correction. | G10: =IF(F10="","",(F10/5)*D10) | H10: =IF(F10="","—",IF(F10=5,"Excellent",IF(F10=4,"Very Good",IF(F10=3,"Good",IF(F10=2,"Needs Improvement","Poor"))))) -> —
A11: 5 | B11: FCR, B/L and Original Document Collection / Endorsement | D11: 0.04 | E11: Arranges preparation, collection, endorsement and submission of FCR, B/L, original BL and related documents from bank, shipping line, forwarder and other offices. | G11: =IF(F11="","",(F11/5)*D11) | H11: =IF(F11="","—",IF(F11=5,"Excellent",IF(F11=4,"Very Good",IF(F11=3,"Good",IF(F11=2,"Needs Improvement","Poor"))))) -> —
A12: 6 | B12: H&M / IKEA / Buyer-Specific Documentation & Online Portal Work | D12: 0.03 | E12: Handles H&M/IKEA documentation, H&M FCR, DAMCO/DEMCO portal upload, loading advice, buyer-specific document requirements and portal monitoring. | G12: =IF(F12="","",(F12/5)*D12) | H12: =IF(F12="","—",IF(F12=5,"Excellent",IF(F12=4,"Very Good",IF(F12=3,"Good",IF(F12=2,"Needs Improvement","Poor"))))) -> —
A13: 7 | B13: Shipping Line, Forwarder, C&F and Loading Advice Coordination | D13: 0.04 | E13: Collects shipment/loading advice from shipping line/forwarder; coordinates with nominated forwarders, C&F agents at Dhaka/Chattogram and marketing department. | F13: 5 | G13: =IF(F13="","",(F13/5)*D13) -> 0.04 | H13: =IF(F13="","—",IF(F13=5,"Excellent",IF(F13=4,"Very Good",IF(F13=3,"Good",IF(F13=2,"Needs Improvement","Poor"))))) -> Excellent
A14: 8 | B14: Shipment, Vessel and Container Movement Monitoring | D14: 0.03 | E14: Monitors feeder/mother vessel sailing, ETA at destination, container movement, cargo release status and destination-wise delivery confirmation certificate preparation. | F14: 5 | G14: =IF(F14="","",(F14/5)*D14) -> 0.03 | H14: =IF(F14="","—",IF(F14=5,"Excellent",IF(F14=4,"Very Good",IF(F14=3,"Good",IF(F14=2,"Needs Improvement","Poor"))))) -> Excellent
A15: 9 | B15: Buyer, Bank, Marketing, Factory and Liaison Communication | D15: 0.03 | E15: Maintains active communication by email/phone with buyers, banks, buying house/liaison office, marketing, factory operation, C&F and other stakeholders. | G15: =IF(F15="","",(F15/5)*D15) | H15: =IF(F15="","—",IF(F15=5,"Excellent",IF(F15=4,"Very Good",IF(F15=3,"Good",IF(F15=2,"Needs Improvement","Poor"))))) -> —
A16: 10 | B16: Back-to-Back L/C Opening & Documentation Control | D16: 0.04 | E16: Opens local/foreign Back-to-Back L/Cs, prepares/submits yarn and fabrics documents, follows bank-related works, Mushok/Delivery Challan, BTMA certificate and LC documentation statements. | F16: out | G16: =IF(F16="","",(F16/5)*D16) -> #VALUE! | H16: =IF(F16="","—",IF(F16=5,"Excellent",IF(F16=4,"Very Good",IF(F16=3,"Good",IF(F16=2,"Needs Improvement","Poor"))))) -> Poor
A17: 11 | B17: Export Statement, MIS, Database and Document Tracking | D17: 0.03 | E17: Updates export document statements, BL/FCR status, invoice folder/network records, export database/storage and department-level reports for management follow-up. | G17: =IF(F17="","",(F17/5)*D17) | H17: =IF(F17="","—",IF(F17=5,"Excellent",IF(F17=4,"Very Good",IF(F17=3,"Good",IF(F17=2,"Needs Improvement","Poor"))))) -> —
A18: 12 | B18: Ocean Freight Voucher, Charges Adjustment and Audit Support | D18: 0.03 | E18: Checks ocean freight vouchers, adjusts freight charges with audit department and supports payment/document-related reconciliation. | F18: 5 | G18: =IF(F18="","",(F18/5)*D18) -> 0.03 | H18: =IF(F18="","—",IF(F18=5,"Excellent",IF(F18=4,"Very Good",IF(F18=3,"Good",IF(F18=2,"Needs Improvement","Poor"))))) -> Excellent
A19: 13 | B19: Process Improvement, Automation & Productivity Initiatives | D19: 0.02 | E19: Improves bond processes, reporting flow, CBMS usage and workflow efficiency through practical automation and productivity initiatives. | G19: =IF(F19="","",(F19/5)*D19) | H19: =IF(F19="","—",IF(F19=5,"Excellent",IF(F19=4,"Very Good",IF(F19=3,"Good",IF(F19=2,"Needs Improvement","Poor"))))) -> —
A20: 14 | B20: Integrity, Confidentiality & Ethical Handling of Export Matters | D20: 0.02 | E20: Maintains honesty, confidentiality and ethical conduct while handling regulatory records, bond documents, official communication and sensitive information. | G20: =IF(F20="","",(F20/5)*D20) | H20: =IF(F20="","—",IF(F20=5,"Excellent",IF(F20=4,"Very Good",IF(F20=3,"Good",IF(F20=2,"Needs Improvement","Poor"))))) -> —
A21: 15 | B21: Accountability, Decision Making & Pressure Handling | D21: 0.03 | E21: Shows ownership, sound judgment and professional decision-making while handling urgent regulatory, audit and operational pressure. | G21: =IF(F21="","",(F21/5)*D21) | H21: =IF(F21="","—",IF(F21=5,"Excellent",IF(F21=4,"Very Good",IF(F21=3,"Good",IF(F21=2,"Needs Improvement","Poor"))))) -> —
A22: TOTAL | D22: =SUM(D7:D21) -> 0.5 | F22: =SUM(F7:F21) -> 15 | G22: =IFERROR(SUM(G7:G21),"")
A23: HOD Block Score (out of 100): | G23: =IFERROR(G22/0.5*100,"") | H23: =IFERROR(IF(G23>=90,"Excellent",IF(G23>=80,"Very Good",IF(G23>=70,"Good",IF(G23>=60,"Needs Improvement","Unsatisfactory")))),"—") -> Excellent
A25: Recommended Actions:
B26: Promotion to
B27: Increment of BDT
B28: No Increment + PIP
B29: PIP / Role Review / Disciplinary Action
A31: HOD Comments (if any) and Signature with Seal and Date:
